odoo/addons/rma_delivery/README.rst
odoo/addons/rma_delivery/__init__.py
odoo/addons/rma_delivery/__manifest__.py
odoo/addons/rma_delivery/i18n/rma_delivery.pot
odoo/addons/rma_delivery/models/__init__.py
odoo/addons/rma_delivery/models/res_company.py
odoo/addons/rma_delivery/models/res_config_settings.py
odoo/addons/rma_delivery/models/rma.py
odoo/addons/rma_delivery/readme/CONFIGURE.rst
odoo/addons/rma_delivery/readme/CONTRIBUTORS.rst
odoo/addons/rma_delivery/readme/DESCRIPTION.rst
odoo/addons/rma_delivery/readme/USAGE.rst
odoo/addons/rma_delivery/static/description/icon.png
odoo/addons/rma_delivery/static/description/index.html
odoo/addons/rma_delivery/tests/__init__.py
odoo/addons/rma_delivery/tests/test_rma_delivery.py
odoo/addons/rma_delivery/views/res_config_settings_views.xml
odoo13_addon_rma_delivery-13.0.1.0.1.dev4.dist-info/METADATA
odoo13_addon_rma_delivery-13.0.1.0.1.dev4.dist-info/WHEEL
odoo13_addon_rma_delivery-13.0.1.0.1.dev4.dist-info/top_level.txt
odoo13_addon_rma_delivery-13.0.1.0.1.dev4.dist-info/RECORD
